{
  "templates_path": {
    "wapiti": "%USERPROFILE%\\AppData\\Local\\Temp\\RestackAPI\\config\\templates\\wapiti_config.json",
    "whatweb": "",
    "zap": ""
  },
  "report_paths" : {
    "wapiti": "%USERPROFILE%\\AppData\\Local\\Temp\\RestackAPI\\reports\\wapiti",
    "whatweb": "%USERPROFILE%\\AppData\\Local\\Temp\\RestackAPI\\temp\\whatweb",
    "zap": "%USERPROFILE%\\AppData\\Local\\Temp\\RestackAPI\\temp\\zap",
    "full": "%USERPROFILE%\\AppData\\Local\\Temp\\RestackAPI\\reports\\full_scan"
  }
}